{
  "project_info": {
    "project_number": "732544100703",
    "firebase_url": "https://anti-spam-26221-default-rtdb.firebaseio.com",
    "project_id": "anti-spam-26221",
    "storage_bucket": "anti-spam-26221.appspot.com"
  },
  "client": [
    {
      "client_info": {
        "mobilesdk_app_id": "1:732544100703:android:a271d167ae32e2bbd9eeea",
        "android_client_info": {
          "package_name": "com.ab.anti_spam"
        }
      },
      "oauth_client": [
        {
          "client_id": "732544100703-khs37mvlj0nn71aqej1bva89vajdohik.apps.googleusercontent.com",
          "client_type": 3
        }
      ],
      "api_key": [
        {
          "current_key": "AIzaSyCNNzv1rHR7W9WlCXRU7tbkUBKgRFzzgYE"
        }
      ],
      "services": {
        "appinvite_service": {
          "other_platform_oauth_client": [
            {
              "client_id": "732544100703-khs37mvlj0nn71aqej1bva89vajdohik.apps.googleusercontent.com",
              "client_type": 3
            }
          ]
        }
      }
    }
  ],
  "configuration_version": "1"
}